<?xml version="1.0" encoding="UTF-8"?>
<objects serializationModel="Studio.02.02.00">
	<object class="AudioFile" id="{510f41ab-80a4-4b7c-9e0d-1d3c84e45176}">
		<property name="assetPath">
			<value>empDioM3.wav</value>
		</property>
		<property name="frequencyInKHz">
			<value>44.0999985</value>
		</property>
		<property name="channelCount">
			<value>2</value>
		</property>
		<property name="length">
			<value>6.7702721088435371</value>
		</property>
		<relationship name="masterAssetFolder">
			<destination>{d024972d-21e3-40eb-ae0d-c3341d926f7a}</destination>
		</relationship>
	</object>
</objects>
